configs/__init__.py
configs/asgi.py
configs/settings.py
configs/urls.py
configs/wsgi.py
wdg_core_file_storage/__init__.py
wdg_core_file_storage/apps.py
wdg_core_file_storage/base.py
wdg_core_file_storage/conf.py
wdg_core_file_storage/constants.py
wdg_core_file_storage/tests.py
wdg_core_file_storage/backends/__init__.py
wdg_core_file_storage/backends/s3.py
wdg_core_file_storage/backends/s3_v1.py
wdg_core_file_storage/backends/storages.py
wdg_core_file_storage/helpers/__init__.py
wdg_core_file_storage/helpers/s3_helpers.py
wdg_core_file_storage/migrations/__init__.py
wdg_core_file_storage/selectors/__init__.py
wdg_core_file_storage/serializers/__init__.py
wdg_core_file_storage/serializers/file_storage_presigned_serializer.py
wdg_core_file_storage/serializers/file_storage_serializer.py
wdg_core_file_storage/services/__init__.py
wdg_core_file_storage/services/save_file_metadata_service.py
wdg_core_file_storage/urls/__init__.py
wdg_core_file_storage/urls/base.py
wdg_core_file_storage/urls/pre_signed.py
wdg_core_file_storage/utils/__init__.py
wdg_core_file_storage/utils/file_manager_util.py
wdg_core_file_storage/utils/file_util.py
wdg_core_file_storage/views/FileStorageViewSet.py
wdg_core_file_storage/views/PresigndFileStorageViewSet.py
wdg_core_file_storage/views/__init__.py
wdg_core_file_storage/wdg_file_metadata/__init__.py
wdg_core_file_storage/wdg_file_metadata/admin.py
wdg_core_file_storage/wdg_file_metadata/apps.py
wdg_core_file_storage/wdg_file_metadata/models.py
wdg_core_file_storage/wdg_file_metadata/views.py
wdg_core_file_storage/wdg_file_metadata/migrations/0001_initial.py
wdg_core_file_storage/wdg_file_metadata/migrations/0002_alter_filestoragemodel_table.py
wdg_core_file_storage/wdg_file_metadata/migrations/__init__.py
wdg_core_file_storage-0.12.0.dist-info/LICENSE
wdg_core_file_storage-0.12.0.dist-info/METADATA
wdg_core_file_storage-0.12.0.dist-info/WHEEL
wdg_core_file_storage-0.12.0.dist-info/top_level.txt
wdg_core_file_storage-0.12.0.dist-info/RECORD
